hermes_storage_nodes/__init__.py
hermes_storage_nodes/arrow_node.py
hermes_storage_nodes/csv_node.py
hermes_storage_nodes/influxdb_client_node.py
hermes_storage_nodes-1.1.0.dist-info/METADATA
hermes_storage_nodes-1.1.0.dist-info/WHEEL
hermes_storage_nodes-1.1.0.dist-info/entry_points.txt
hermes_storage_nodes-1.1.0.dist-info/RECORD
