Metadata-Version: 2.4
Name: hermes-storage-nodes
Version: 1.1.0
Summary: An utility to facilitate the building of fman build system based projects
Author-email: floris vernieuwe <floris@vernieuwe.eu>
Requires-Python: >=3.10
Requires-Dist: influxdb-client>=1.48.0
Requires-Dist: node-hermes-core>=1.2.0
Requires-Dist: pandas>=2.2.3
Requires-Dist: polars>=1.24.0
Requires-Dist: pyarrow>=19.0.1
Requires-Dist: pydantic>=2.10.6
